{"id":"535851_1354106_2017-06-07_102e","type":"Feature","geometry":{"coordinates":[[[-107.23703156667844,32.512876509367516],[-107.18102704245528,32.739315894124516],[-107.04386960228878,32.74169831755806],[-107.03876267632513,32.5163506103479],[-107.23703156667844,32.512876509367516]]],"type":"Polygon"},"properties":{"acquired":"2017-06-07T17:02:47.504512Z","anomalous_pixels":0,"black_fill":0.39,"cloud_cover":0,"columns":8000,"epsg_code":32613,"grid_cell":"1354106","ground_control":true,"gsd":3.9,"instrument":"PS2","item_type":"PSOrthoTile","origin_x":283500,"origin_y":3624500,"pixel_resolution":3.125,"provider":"planetscope","published":"2017-06-08T07:04:01Z","publishing_stage":"finalized","quality_category":"standard","rows":8000,"satellite_id":"102e","strip_id":"535851","sun_azimuth":101.7,"sun_elevation":60.9,"updated":"2017-06-08T07:04:01Z","usable_data":0.6,"view_angle":0.1}}
