{
    "type": "FeatureCollection",
    "features": [
        {
            "type": "Feature",
            "properties": {},
            "id": 1,
            "geometry": {
                "type": "Polygon",
                "coordinates": [
                    [
                        [
                            -106.8352815,
                            32.3410906
                        ],
                        [
                            -106.8352815,
                            32.3610906
                        ],
                        [
                            -106.8612815,
                            32.3610906
                        ],
                        [
                            -106.8612815,
                            32.3410906
                        ],
                        [
                            -106.8352815,
                            32.3410906
                        ]
                    ]
                ]
            }
        }
    ]
}